{
  "Broncos": {
    "team": "Broncos",
    "conference": "AFC",
    "division": "AFC West",
    "games": 17,
    "schedule": [
      {
        "opponent": "Chiefs",
        "homeAway": "home",
        "date": "",
        "gameId": "544735514",
        "oppElo": null
      },
      {
        "opponent": "Seahawks",
        "homeAway": "home",
        "date": "",
        "gameId": "544735488",
        "oppElo": null
      },
      {
        "opponent": "Dolphins",
        "homeAway": "home",
        "date": "",
        "gameId": "544735481",
        "oppElo": null
      },
      {
        "opponent": "Bills",
        "homeAway": "away",
        "date": "",
        "gameId": "544735460",
        "oppElo": null
      },
      {
        "opponent": "Buccaneers",
        "homeAway": "home",
        "date": "",
        "gameId": "544735442",
        "oppElo": null
      },
      {
        "opponent": "Cardinals",
        "homeAway": "away",
        "date": "",
        "gameId": "544735418",
        "oppElo": null
      },
      {
        "opponent": "Raiders",
        "homeAway": "home",
        "date": "",
        "gameId": "544735395",
        "oppElo": null
      },
      {
        "opponent": "Titans",
        "homeAway": "home",
        "date": "",
        "gameId": "544735385",
        "oppElo": null
      },
      {
        "opponent": "Raiders",
        "homeAway": "away",
        "date": "",
        "gameId": "544735374",
        "oppElo": null
      },
      {
        "opponent": "Chiefs",
        "homeAway": "away",
        "date": "",
        "gameId": "544735354",
        "oppElo": null
      },
      {
        "opponent": "Chargers",
        "homeAway": "home",
        "date": "",
        "gameId": "544735339",
        "oppElo": null
      },
      {
        "opponent": "Ravens",
        "homeAway": "away",
        "date": "",
        "gameId": "544735328",
        "oppElo": null
      },
      {
        "opponent": "Jets",
        "homeAway": "home",
        "date": "",
        "gameId": "544735315",
        "oppElo": null
      },
      {
        "opponent": "Chargers",
        "homeAway": "away",
        "date": "",
        "gameId": "544735307",
        "oppElo": null
      },
      {
        "opponent": "Patriots",
        "homeAway": "away",
        "date": "",
        "gameId": "544735281",
        "oppElo": null
      },
      {
        "opponent": "Rams",
        "homeAway": "home",
        "date": "",
        "gameId": "544735275",
        "oppElo": null
      },
      {
        "opponent": "49ers",
        "homeAway": "away",
        "date": "",
        "gameId": "544735248",
        "oppElo": null
      }
    ]
  },
  "Chiefs": {
    "team": "Chiefs",
    "conference": "AFC",
    "division": "AFC West",
    "games": 17,
    "schedule": [
      {
        "opponent": "Broncos",
        "homeAway": "away",
        "date": "",
        "gameId": "544735514",
        "oppElo": null
      },
      {
        "opponent": "Raiders",
        "homeAway": "away",
        "date": "",
        "gameId": "544735500",
        "oppElo": null
      },
      {
        "opponent": "49ers",
        "homeAway": "home",
        "date": "",
        "gameId": "544735469",
        "oppElo": null
      },
      {
        "opponent": "Cardinals",
        "homeAway": "home",
        "date": "",
        "gameId": "544735453",
        "oppElo": null
      },
      {
        "opponent": "Chargers",
        "homeAway": "home",
        "date": "",
        "gameId": "544735438",
        "oppElo": null
      },
      {
        "opponent": "Seahawks",
        "homeAway": "away",
        "date": "",
        "gameId": "544735424",
        "oppElo": null
      },
      {
        "opponent": "Chargers",
        "homeAway": "away",
        "date": "",
        "gameId": "544735415",
        "oppElo": null
      },
      {
        "opponent": "Bills",
        "homeAway": "home",
        "date": "",
        "gameId": "544735396",
        "oppElo": null
      },
      {
        "opponent": "Jets",
        "homeAway": "away",
        "date": "",
        "gameId": "544735384",
        "oppElo": null
      },
      {
        "opponent": "Colts",
        "homeAway": "home",
        "date": "",
        "gameId": "544735378",
        "oppElo": null
      },
      {
        "opponent": "Broncos",
        "homeAway": "home",
        "date": "",
        "gameId": "544735354",
        "oppElo": null
      },
      {
        "opponent": "Rams",
        "homeAway": "away",
        "date": "",
        "gameId": "544735337",
        "oppElo": null
      },
      {
        "opponent": "Patriots",
        "homeAway": "home",
        "date": "",
        "gameId": "544735309",
        "oppElo": null
      },
      {
        "opponent": "Raiders",
        "homeAway": "home",
        "date": "",
        "gameId": "544735308",
        "oppElo": null
      },
      {
        "opponent": "Dolphins",
        "homeAway": "away",
        "date": "",
        "gameId": "544735277",
        "oppElo": null
      },
      {
        "opponent": "Steelers",
        "homeAway": "away",
        "date": "",
        "gameId": "544735261",
        "oppElo": null
      },
      {
        "opponent": "Panthers",
        "homeAway": "home",
        "date": "",
        "gameId": "544735245",
        "oppElo": null
      }
    ]
  },
  "49ers": {
    "team": "49ers",
    "conference": "NFC",
    "division": "NFC West",
    "games": 17,
    "schedule": [
      {
        "opponent": "Chargers",
        "homeAway": "home",
        "date": "",
        "gameId": "544735501",
        "oppElo": null
      },
      {
        "opponent": "Eagles",
        "homeAway": "away",
        "date": "",
        "gameId": "544735497",
        "oppElo": null
      },
      {
        "opponent": "Chiefs",
        "homeAway": "away",
        "date": "",
        "gameId": "544735469",
        "oppElo": null
      },
      {
        "opponent": "Seahawks",
        "homeAway": "home",
        "date": "",
        "gameId": "544735454",
        "oppElo": null
      },
      {
        "opponent": "Cowboys",
        "homeAway": "away",
        "date": "",
        "gameId": "544735441",
        "oppElo": null
      },
      {
        "opponent": "Raiders",
        "homeAway": "away",
        "date": "",
        "gameId": "544735429",
        "oppElo": null
      },
      {
        "opponent": "Rams",
        "homeAway": "home",
        "date": "",
        "gameId": "544735411",
        "oppElo": null
      },
      {
        "opponent": "Cardinals",
        "homeAway": "away",
        "date": "",
        "gameId": "544735393",
        "oppElo": null
      },
      {
        "opponent": "Bears",
        "homeAway": "away",
        "date": "",
        "gameId": "544735371",
        "oppElo": null
      },
      {
        "opponent": "Dolphins",
        "homeAway": "away",
        "date": "",
        "gameId": "544735356",
        "oppElo": null
      },
      {
        "opponent": "Saints",
        "homeAway": "home",
        "date": "",
        "gameId": "544735345",
        "oppElo": null
      },
      {
        "opponent": "Giants",
        "homeAway": "home",
        "date": "",
        "gameId": "544735333",
        "oppElo": null
      },
      {
        "opponent": "Commanders",
        "homeAway": "home",
        "date": "",
        "gameId": "544735314",
        "oppElo": null
      },
      {
        "opponent": "Seahawks",
        "homeAway": "away",
        "date": "",
        "gameId": "544735304",
        "oppElo": null
      },
      {
        "opponent": "Rams",
        "homeAway": "away",
        "date": "",
        "gameId": "544735292",
        "oppElo": null
      },
      {
        "opponent": "Cardinals",
        "homeAway": "home",
        "date": "",
        "gameId": "544735262",
        "oppElo": null
      },
      {
        "opponent": "Broncos",
        "homeAway": "home",
        "date": "",
        "gameId": "544735248",
        "oppElo": null
      }
    ]
  },
  "Chargers": {
    "team": "Chargers",
    "conference": "AFC",
    "division": "AFC West",
    "games": 17,
    "schedule": [
      {
        "opponent": "49ers",
        "homeAway": "away",
        "date": "",
        "gameId": "544735501",
        "oppElo": null
      },
      {
        "opponent": "Rams",
        "homeAway": "home",
        "date": "",
        "gameId": "544735485",
        "oppElo": null
      },
      {
        "opponent": "Patriots",
        "homeAway": "away",
        "date": "",
        "gameId": "544735483",
        "oppElo": null
      },
      {
        "opponent": "Raiders",
        "homeAway": "home",
        "date": "",
        "gameId": "544735468",
        "oppElo": null
      },
      {
        "opponent": "Chiefs",
        "homeAway": "away",
        "date": "",
        "gameId": "544735438",
        "oppElo": null
      },
      {
        "opponent": "Jets",
        "homeAway": "home",
        "date": "",
        "gameId": "544735433",
        "oppElo": null
      },
      {
        "opponent": "Chiefs",
        "homeAway": "home",
        "date": "",
        "gameId": "544735415",
        "oppElo": null
      },
      {
        "opponent": "Browns",
        "homeAway": "away",
        "date": "",
        "gameId": "544735403",
        "oppElo": null
      },
      {
        "opponent": "Dolphins",
        "homeAway": "home",
        "date": "",
        "gameId": "544735383",
        "oppElo": null
      },
      {
        "opponent": "Seahawks",
        "homeAway": "home",
        "date": "",
        "gameId": "544735372",
        "oppElo": null
      },
      {
        "opponent": "Broncos",
        "homeAway": "away",
        "date": "",
        "gameId": "544735339",
        "oppElo": null
      },
      {
        "opponent": "Falcons",
        "homeAway": "home",
        "date": "",
        "gameId": "544735327",
        "oppElo": null
      },
      {
        "opponent": "Bills",
        "homeAway": "away",
        "date": "",
        "gameId": "544735316",
        "oppElo": null
      },
      {
        "opponent": "Broncos",
        "homeAway": "home",
        "date": "",
        "gameId": "544735307",
        "oppElo": null
      },
      {
        "opponent": "Raiders",
        "homeAway": "away",
        "date": "",
        "gameId": "544735286",
        "oppElo": null
      },
      {
        "opponent": "Texans",
        "homeAway": "home",
        "date": "",
        "gameId": "544735268",
        "oppElo": null
      },
      {
        "opponent": "Cardinals",
        "homeAway": "away",
        "date": "",
        "gameId": "544735251",
        "oppElo": null
      }
    ]
  },
  "Cowboys": {
    "team": "Cowboys",
    "conference": "NFC",
    "division": "NFC East",
    "games": 17,
    "schedule": [
      {
        "opponent": "Commanders",
        "homeAway": "home",
        "date": "",
        "gameId": "544735512",
        "oppElo": null
      },
      {
        "opponent": "Jaguars",
        "homeAway": "away",
        "date": "",
        "gameId": "544735491",
        "oppElo": null
      },
      {
        "opponent": "Rams",
        "homeAway": "away",
        "date": "",
        "gameId": "544735484",
        "oppElo": null
      },
      {
        "opponent": "Colts",
        "homeAway": "away",
        "date": "",
        "gameId": "544735465",
        "oppElo": null
      },
      {
        "opponent": "49ers",
        "homeAway": "home",
        "date": "",
        "gameId": "544735441",
        "oppElo": null
      },
      {
        "opponent": "Giants",
        "homeAway": "home",
        "date": "",
        "gameId": "544735422",
        "oppElo": null
      },
      {
        "opponent": "Commanders",
        "homeAway": "away",
        "date": "",
        "gameId": "544735409",
        "oppElo": null
      },
      {
        "opponent": "Bears",
        "homeAway": "home",
        "date": "",
        "gameId": "544735388",
        "oppElo": null
      },
      {
        "opponent": "Eagles",
        "homeAway": "away",
        "date": "",
        "gameId": "544735370",
        "oppElo": null
      },
      {
        "opponent": "Bengals",
        "homeAway": "away",
        "date": "",
        "gameId": "544735364",
        "oppElo": null
      },
      {
        "opponent": "Titans",
        "homeAway": "home",
        "date": "",
        "gameId": "544735350",
        "oppElo": null
      },
      {
        "opponent": "Texans",
        "homeAway": "home",
        "date": "",
        "gameId": "544735324",
        "oppElo": null
      },
      {
        "opponent": "Saints",
        "homeAway": "away",
        "date": "",
        "gameId": "544735310",
        "oppElo": null
      },
      {
        "opponent": "Eagles",
        "homeAway": "home",
        "date": "",
        "gameId": "544735293",
        "oppElo": null
      },
      {
        "opponent": "Cardinals",
        "homeAway": "home",
        "date": "",
        "gameId": "544735290",
        "oppElo": null
      },
      {
        "opponent": "Seahawks",
        "homeAway": "away",
        "date": "",
        "gameId": "544735270",
        "oppElo": null
      },
      {
        "opponent": "Giants",
        "homeAway": "away",
        "date": "",
        "gameId": "544735259",
        "oppElo": null
      }
    ]
  },
  "Commanders": {
    "team": "Commanders",
    "conference": "NFC",
    "division": "NFC East",
    "games": 17,
    "schedule": [
      {
        "opponent": "Cowboys",
        "homeAway": "away",
        "date": "",
        "gameId": "544735512",
        "oppElo": null
      },
      {
        "opponent": "Titans",
        "homeAway": "away",
        "date": "",
        "gameId": "544735492",
        "oppElo": null
      },
      {
        "opponent": "Vikings",
        "homeAway": "home",
        "date": "",
        "gameId": "544735472",
        "oppElo": null
      },
      {
        "opponent": "Rams",
        "homeAway": "home",
        "date": "",
        "gameId": "544735456",
        "oppElo": null
      },
      {
        "opponent": "Eagles",
        "homeAway": "away",
        "date": "",
        "gameId": "544735439",
        "oppElo": null
      },
      {
        "opponent": "Giants",
        "homeAway": "away",
        "date": "",
        "gameId": "544735430",
        "oppElo": null
      },
      {
        "opponent": "Cowboys",
        "homeAway": "home",
        "date": "",
        "gameId": "544735409",
        "oppElo": null
      },
      {
        "opponent": "Colts",
        "homeAway": "home",
        "date": "",
        "gameId": "544735392",
        "oppElo": null
      },
      {
        "opponent": "Falcons",
        "homeAway": "away",
        "date": "",
        "gameId": "544735377",
        "oppElo": null
      },
      {
        "opponent": "Cardinals",
        "homeAway": "away",
        "date": "",
        "gameId": "544735355",
        "oppElo": null
      },
      {
        "opponent": "Browns",
        "homeAway": "away",
        "date": "",
        "gameId": "544735343",
        "oppElo": null
      },
      {
        "opponent": "Eagles",
        "homeAway": "home",
        "date": "",
        "gameId": "544735326",
        "oppElo": null
      },
      {
        "opponent": "49ers",
        "homeAway": "away",
        "date": "",
        "gameId": "544735314",
        "oppElo": null
      },
      {
        "opponent": "Giants",
        "homeAway": "home",
        "date": "",
        "gameId": "544735301",
        "oppElo": null
      },
      {
        "opponent": "Seahawks",
        "homeAway": "home",
        "date": "",
        "gameId": "544735287",
        "oppElo": null
      },
      {
        "opponent": "Jaguars",
        "homeAway": "home",
        "date": "",
        "gameId": "544735274",
        "oppElo": null
      },
      {
        "opponent": "Texans",
        "homeAway": "away",
        "date": "",
        "gameId": "544735254",
        "oppElo": null
      }
    ]
  },
  "Lions": {
    "team": "Lions",
    "conference": "NFC",
    "division": "NFC North",
    "games": 17,
    "schedule": [
      {
        "opponent": "Falcons",
        "homeAway": "home",
        "date": "",
        "gameId": "544735508",
        "oppElo": null
      },
      {
        "opponent": "Bills",
        "homeAway": "away",
        "date": "",
        "gameId": "544735489",
        "oppElo": null
      },
      {
        "opponent": "Packers",
        "homeAway": "home",
        "date": "",
        "gameId": "544735478",
        "oppElo": null
      },
      {
        "opponent": "Patriots",
        "homeAway": "away",
        "date": "",
        "gameId": "544735464",
        "oppElo": null
      },
      {
        "opponent": "Jets",
        "homeAway": "home",
        "date": "",
        "gameId": "544735444",
        "oppElo": null
      },
      {
        "opponent": "Bears",
        "homeAway": "away",
        "date": "",
        "gameId": "544735432",
        "oppElo": null
      },
      {
        "opponent": "Seahawks",
        "homeAway": "home",
        "date": "",
        "gameId": "544735413",
        "oppElo": null
      },
      {
        "opponent": "Bears",
        "homeAway": "home",
        "date": "",
        "gameId": "544735408",
        "oppElo": null
      },
      {
        "opponent": "Saints",
        "homeAway": "away",
        "date": "",
        "gameId": "544735386",
        "oppElo": null
      },
      {
        "opponent": "Vikings",
        "homeAway": "home",
        "date": "",
        "gameId": "544735363",
        "oppElo": null
      },
      {
        "opponent": "Dolphins",
        "homeAway": "home",
        "date": "",
        "gameId": "544735347",
        "oppElo": null
      },
      {
        "opponent": "Panthers",
        "homeAway": "away",
        "date": "",
        "gameId": "544735336",
        "oppElo": null
      },
      {
        "opponent": "Giants",
        "homeAway": "away",
        "date": "",
        "gameId": "544735313",
        "oppElo": null
      },
      {
        "opponent": "Buccaneers",
        "homeAway": "home",
        "date": "",
        "gameId": "544735306",
        "oppElo": null
      },
      {
        "opponent": "Titans",
        "homeAway": "away",
        "date": "",
        "gameId": "544735291",
        "oppElo": null
      },
      {
        "opponent": "Packers",
        "homeAway": "away",
        "date": "",
        "gameId": "544735263",
        "oppElo": null
      },
      {
        "opponent": "Vikings",
        "homeAway": "away",
        "date": "",
        "gameId": "544735256",
        "oppElo": null
      }
    ]
  },
  "Falcons": {
    "team": "Falcons",
    "conference": "NFC",
    "division": "NFC South",
    "games": 17,
    "schedule": [
      {
        "opponent": "Lions",
        "homeAway": "away",
        "date": "",
        "gameId": "544735508",
        "oppElo": null
      },
      {
        "opponent": "Buccaneers",
        "homeAway": "away",
        "date": "",
        "gameId": "544735496",
        "oppElo": null
      },
      {
        "opponent": "Panthers",
        "homeAway": "home",
        "date": "",
        "gameId": "544735473",
        "oppElo": null
      },
      {
        "opponent": "Packers",
        "homeAway": "home",
        "date": "",
        "gameId": "544735461",
        "oppElo": null
      },
      {
        "opponent": "Bears",
        "homeAway": "home",
        "date": "",
        "gameId": "544735447",
        "oppElo": null
      },
      {
        "opponent": "Ravens",
        "homeAway": "away",
        "date": "",
        "gameId": "544735431",
        "oppElo": null
      },
      {
        "opponent": "Panthers",
        "homeAway": "away",
        "date": "",
        "gameId": "544735414",
        "oppElo": null
      },
      {
        "opponent": "Saints",
        "homeAway": "away",
        "date": "",
        "gameId": "544735407",
        "oppElo": null
      },
      {
        "opponent": "Commanders",
        "homeAway": "home",
        "date": "",
        "gameId": "544735377",
        "oppElo": null
      },
      {
        "opponent": "Buccaneers",
        "homeAway": "home",
        "date": "",
        "gameId": "544735357",
        "oppElo": null
      },
      {
        "opponent": "Steelers",
        "homeAway": "home",
        "date": "",
        "gameId": "544735340",
        "oppElo": null
      },
      {
        "opponent": "Chargers",
        "homeAway": "away",
        "date": "",
        "gameId": "544735327",
        "oppElo": null
      },
      {
        "opponent": "Vikings",
        "homeAway": "away",
        "date": "",
        "gameId": "544735319",
        "oppElo": null
      },
      {
        "opponent": "Saints",
        "homeAway": "home",
        "date": "",
        "gameId": "544735299",
        "oppElo": null
      },
      {
        "opponent": "Browns",
        "homeAway": "away",
        "date": "",
        "gameId": "544735285",
        "oppElo": null
      },
      {
        "opponent": "Bengals",
        "homeAway": "home",
        "date": "",
        "gameId": "544735264",
        "oppElo": null
      },
      {
        "opponent": "Rams",
        "homeAway": "away",
        "date": "",
        "gameId": "544735257",
        "oppElo": null
      }
    ]
  },
  "Seahawks": {
    "team": "Seahawks",
    "conference": "NFC",
    "division": "NFC West",
    "games": 17,
    "schedule": [
      {
        "opponent": "Eagles",
        "homeAway": "home",
        "date": "",
        "gameId": "544735505",
        "oppElo": null
      },
      {
        "opponent": "Broncos",
        "homeAway": "away",
        "date": "",
        "gameId": "544735488",
        "oppElo": null
      },
      {
        "opponent": "Cardinals",
        "homeAway": "away",
        "date": "",
        "gameId": "544735475",
        "oppElo": null
      },
      {
        "opponent": "49ers",
        "homeAway": "away",
        "date": "",
        "gameId": "544735454",
        "oppElo": null
      },
      {
        "opponent": "Patriots",
        "homeAway": "away",
        "date": "",
        "gameId": "544735450",
        "oppElo": null
      },
      {
        "opponent": "Chiefs",
        "homeAway": "home",
        "date": "",
        "gameId": "544735424",
        "oppElo": null
      },
      {
        "opponent": "Lions",
        "homeAway": "away",
        "date": "",
        "gameId": "544735413",
        "oppElo": null
      },
      {
        "opponent": "Giants",
        "homeAway": "away",
        "date": "",
        "gameId": "544735399",
        "oppElo": null
      },
      {
        "opponent": "Raiders",
        "homeAway": "home",
        "date": "",
        "gameId": "544735387",
        "oppElo": null
      },
      {
        "opponent": "Chargers",
        "homeAway": "away",
        "date": "",
        "gameId": "544735372",
        "oppElo": null
      },
      {
        "opponent": "Rams",
        "homeAway": "away",
        "date": "",
        "gameId": "544735352",
        "oppElo": null
      },
      {
        "opponent": "Cardinals",
        "homeAway": "home",
        "date": "",
        "gameId": "544735346",
        "oppElo": null
      },
      {
        "opponent": "Rams",
        "homeAway": "home",
        "date": "",
        "gameId": "544735335",
        "oppElo": null
      },
      {
        "opponent": "49ers",
        "homeAway": "home",
        "date": "",
        "gameId": "544735304",
        "oppElo": null
      },
      {
        "opponent": "Commanders",
        "homeAway": "away",
        "date": "",
        "gameId": "544735287",
        "oppElo": null
      },
      {
        "opponent": "Cowboys",
        "homeAway": "home",
        "date": "",
        "gameId": "544735270",
        "oppElo": null
      },
      {
        "opponent": "Buccaneers",
        "homeAway": "home",
        "date": "",
        "gameId": "544735253",
        "oppElo": null
      }
    ]
  },
  "Eagles": {
    "team": "Eagles",
    "conference": "NFC",
    "division": "NFC East",
    "games": 17,
    "schedule": [
      {
        "opponent": "Seahawks",
        "homeAway": "away",
        "date": "",
        "gameId": "544735505",
        "oppElo": null
      },
      {
        "opponent": "49ers",
        "homeAway": "home",
        "date": "",
        "gameId": "544735497",
        "oppElo": null
      },
      {
        "opponent": "Steelers",
        "homeAway": "away",
        "date": "",
        "gameId": "544735480",
        "oppElo": null
      },
      {
        "opponent": "Jaguars",
        "homeAway": "away",
        "date": "",
        "gameId": "544735467",
        "oppElo": null
      },
      {
        "opponent": "Commanders",
        "homeAway": "home",
        "date": "",
        "gameId": "544735439",
        "oppElo": null
      },
      {
        "opponent": "Cardinals",
        "homeAway": "home",
        "date": "",
        "gameId": "544735423",
        "oppElo": null
      },
      {
        "opponent": "Colts",
        "homeAway": "away",
        "date": "",
        "gameId": "544735417",
        "oppElo": null
      },
      {
        "opponent": "Rams",
        "homeAway": "away",
        "date": "",
        "gameId": "544735404",
        "oppElo": null
      },
      {
        "opponent": "Packers",
        "homeAway": "home",
        "date": "",
        "gameId": "544735382",
        "oppElo": null
      },
      {
        "opponent": "Cowboys",
        "homeAway": "home",
        "date": "",
        "gameId": "544735370",
        "oppElo": null
      },
      {
        "opponent": "Giants",
        "homeAway": "away",
        "date": "",
        "gameId": "544735353",
        "oppElo": null
      },
      {
        "opponent": "Texans",
        "homeAway": "home",
        "date": "",
        "gameId": "544735344",
        "oppElo": null
      },
      {
        "opponent": "Commanders",
        "homeAway": "away",
        "date": "",
        "gameId": "544735326",
        "oppElo": null
      },
      {
        "opponent": "Cowboys",
        "homeAway": "away",
        "date": "",
        "gameId": "544735293",
        "oppElo": null
      },
      {
        "opponent": "Panthers",
        "homeAway": "away",
        "date": "",
        "gameId": "544735280",
        "oppElo": null
      },
      {
        "opponent": "Giants",
        "homeAway": "home",
        "date": "",
        "gameId": "544735276",
        "oppElo": null
      },
      {
        "opponent": "Titans",
        "homeAway": "home",
        "date": "",
        "gameId": "544735252",
        "oppElo": null
      }
    ]
  },
  "Raiders": {
    "team": "Raiders",
    "conference": "AFC",
    "division": "AFC West",
    "games": 17,
    "schedule": [
      {
        "opponent": "Cardinals",
        "homeAway": "home",
        "date": "",
        "gameId": "544735502",
        "oppElo": null
      },
      {
        "opponent": "Chiefs",
        "homeAway": "home",
        "date": "",
        "gameId": "544735500",
        "oppElo": null
      },
      {
        "opponent": "Jets",
        "homeAway": "away",
        "date": "",
        "gameId": "544735482",
        "oppElo": null
      },
      {
        "opponent": "Chargers",
        "homeAway": "away",
        "date": "",
        "gameId": "544735468",
        "oppElo": null
      },
      {
        "opponent": "Bengals",
        "homeAway": "away",
        "date": "",
        "gameId": "544735449",
        "oppElo": null
      },
      {
        "opponent": "49ers",
        "homeAway": "home",
        "date": "",
        "gameId": "544735429",
        "oppElo": null
      },
      {
        "opponent": "Patriots",
        "homeAway": "home",
        "date": "",
        "gameId": "544735416",
        "oppElo": null
      },
      {
        "opponent": "Broncos",
        "homeAway": "away",
        "date": "",
        "gameId": "544735395",
        "oppElo": null
      },
      {
        "opponent": "Seahawks",
        "homeAway": "away",
        "date": "",
        "gameId": "544735387",
        "oppElo": null
      },
      {
        "opponent": "Broncos",
        "homeAway": "home",
        "date": "",
        "gameId": "544735374",
        "oppElo": null
      },
      {
        "opponent": "Bills",
        "homeAway": "home",
        "date": "",
        "gameId": "544735362",
        "oppElo": null
      },
      {
        "opponent": "Jaguars",
        "homeAway": "home",
        "date": "",
        "gameId": "544735348",
        "oppElo": null
      },
      {
        "opponent": "Rams",
        "homeAway": "away",
        "date": "",
        "gameId": "544735317",
        "oppElo": null
      },
      {
        "opponent": "Chiefs",
        "homeAway": "away",
        "date": "",
        "gameId": "544735308",
        "oppElo": null
      },
      {
        "opponent": "Chargers",
        "homeAway": "home",
        "date": "",
        "gameId": "544735286",
        "oppElo": null
      },
      {
        "opponent": "Dolphins",
        "homeAway": "away",
        "date": "",
        "gameId": "544735269",
        "oppElo": null
      },
      {
        "opponent": "Saints",
        "homeAway": "home",
        "date": "",
        "gameId": "544735255",
        "oppElo": null
      }
    ]
  },
  "Cardinals": {
    "team": "Cardinals",
    "conference": "NFC",
    "division": "NFC West",
    "games": 17,
    "schedule": [
      {
        "opponent": "Raiders",
        "homeAway": "away",
        "date": "",
        "gameId": "544735502",
        "oppElo": null
      },
      {
        "opponent": "Giants",
        "homeAway": "home",
        "date": "",
        "gameId": "544735495",
        "oppElo": null
      },
      {
        "opponent": "Seahawks",
        "homeAway": "home",
        "date": "",
        "gameId": "544735475",
        "oppElo": null
      },
      {
        "opponent": "Chiefs",
        "homeAway": "away",
        "date": "",
        "gameId": "544735453",
        "oppElo": null
      },
      {
        "opponent": "Rams",
        "homeAway": "away",
        "date": "",
        "gameId": "544735445",
        "oppElo": null
      },
      {
        "opponent": "Eagles",
        "homeAway": "away",
        "date": "",
        "gameId": "544735423",
        "oppElo": null
      },
      {
        "opponent": "Broncos",
        "homeAway": "home",
        "date": "",
        "gameId": "544735418",
        "oppElo": null
      },
      {
        "opponent": "Panthers",
        "homeAway": "home",
        "date": "",
        "gameId": "544735402",
        "oppElo": null
      },
      {
        "opponent": "49ers",
        "homeAway": "home",
        "date": "",
        "gameId": "544735393",
        "oppElo": null
      },
      {
        "opponent": "Rams",
        "homeAway": "home",
        "date": "",
        "gameId": "544735373",
        "oppElo": null
      },
      {
        "opponent": "Commanders",
        "homeAway": "home",
        "date": "",
        "gameId": "544735355",
        "oppElo": null
      },
      {
        "opponent": "Seahawks",
        "homeAway": "away",
        "date": "",
        "gameId": "544735346",
        "oppElo": null
      },
      {
        "opponent": "Jets",
        "homeAway": "away",
        "date": "",
        "gameId": "544735323",
        "oppElo": null
      },
      {
        "opponent": "Packers",
        "homeAway": "away",
        "date": "",
        "gameId": "544735295",
        "oppElo": null
      },
      {
        "opponent": "Cowboys",
        "homeAway": "away",
        "date": "",
        "gameId": "544735290",
        "oppElo": null
      },
      {
        "opponent": "49ers",
        "homeAway": "away",
        "date": "",
        "gameId": "544735262",
        "oppElo": null
      },
      {
        "opponent": "Chargers",
        "homeAway": "home",
        "date": "",
        "gameId": "544735251",
        "oppElo": null
      }
    ]
  },
  "Saints": {
    "team": "Saints",
    "conference": "NFC",
    "division": "NFC South",
    "games": 17,
    "schedule": [
      {
        "opponent": "Ravens",
        "homeAway": "home",
        "date": "",
        "gameId": "544735504",
        "oppElo": null
      },
      {
        "opponent": "Bears",
        "homeAway": "away",
        "date": "",
        "gameId": "544735486",
        "oppElo": null
      },
      {
        "opponent": "Buccaneers",
        "homeAway": "home",
        "date": "",
        "gameId": "544735479",
        "oppElo": null
      },
      {
        "opponent": "Browns",
        "homeAway": "home",
        "date": "",
        "gameId": "544735457",
        "oppElo": null
      },
      {
        "opponent": "Panthers",
        "homeAway": "home",
        "date": "",
        "gameId": "544735437",
        "oppElo": null
      },
      {
        "opponent": "Steelers",
        "homeAway": "away",
        "date": "",
        "gameId": "544735426",
        "oppElo": null
      },
      {
        "opponent": "Bengals",
        "homeAway": "away",
        "date": "",
        "gameId": "544735419",
        "oppElo": null
      },
      {
        "opponent": "Falcons",
        "homeAway": "home",
        "date": "",
        "gameId": "544735407",
        "oppElo": null
      },
      {
        "opponent": "Lions",
        "homeAway": "home",
        "date": "",
        "gameId": "544735386",
        "oppElo": null
      },
      {
        "opponent": "Buccaneers",
        "homeAway": "away",
        "date": "",
        "gameId": "544735380",
        "oppElo": null
      },
      {
        "opponent": "Panthers",
        "homeAway": "away",
        "date": "",
        "gameId": "544735366",
        "oppElo": null
      },
      {
        "opponent": "49ers",
        "homeAway": "away",
        "date": "",
        "gameId": "544735345",
        "oppElo": null
      },
      {
        "opponent": "Cowboys",
        "homeAway": "home",
        "date": "",
        "gameId": "544735310",
        "oppElo": null
      },
      {
        "opponent": "Falcons",
        "homeAway": "away",
        "date": "",
        "gameId": "544735299",
        "oppElo": null
      },
      {
        "opponent": "Packers",
        "homeAway": "away",
        "date": "",
        "gameId": "544735284",
        "oppElo": null
      },
      {
        "opponent": "Vikings",
        "homeAway": "home",
        "date": "",
        "gameId": "544735267",
        "oppElo": null
      },
      {
        "opponent": "Raiders",
        "homeAway": "away",
        "date": "",
        "gameId": "544735255",
        "oppElo": null
      }
    ]
  },
  "Ravens": {
    "team": "Ravens",
    "conference": "AFC",
    "division": "AFC North",
    "games": 17,
    "schedule": [
      {
        "opponent": "Saints",
        "homeAway": "away",
        "date": "",
        "gameId": "544735504",
        "oppElo": null
      },
      {
        "opponent": "Texans",
        "homeAway": "home",
        "date": "",
        "gameId": "544735494",
        "oppElo": null
      },
      {
        "opponent": "Browns",
        "homeAway": "away",
        "date": "",
        "gameId": "544735470",
        "oppElo": null
      },
      {
        "opponent": "Steelers",
        "homeAway": "home",
        "date": "",
        "gameId": "544735463",
        "oppElo": null
      },
      {
        "opponent": "Jaguars",
        "homeAway": "away",
        "date": "",
        "gameId": "544735446",
        "oppElo": null
      },
      {
        "opponent": "Falcons",
        "homeAway": "home",
        "date": "",
        "gameId": "544735431",
        "oppElo": null
      },
      {
        "opponent": "Titans",
        "homeAway": "home",
        "date": "",
        "gameId": "544735420",
        "oppElo": null
      },
      {
        "opponent": "Bengals",
        "homeAway": "home",
        "date": "",
        "gameId": "544735397",
        "oppElo": null
      },
      {
        "opponent": "Giants",
        "homeAway": "home",
        "date": "",
        "gameId": "544735368",
        "oppElo": null
      },
      {
        "opponent": "Patriots",
        "homeAway": "away",
        "date": "",
        "gameId": "544735359",
        "oppElo": null
      },
      {
        "opponent": "Panthers",
        "homeAway": "away",
        "date": "",
        "gameId": "544735341",
        "oppElo": null
      },
      {
        "opponent": "Broncos",
        "homeAway": "home",
        "date": "",
        "gameId": "544735328",
        "oppElo": null
      },
      {
        "opponent": "Buccaneers",
        "homeAway": "home",
        "date": "",
        "gameId": "544735320",
        "oppElo": null
      },
      {
        "opponent": "Steelers",
        "homeAway": "away",
        "date": "",
        "gameId": "544735300",
        "oppElo": null
      },
      {
        "opponent": "Bengals",
        "homeAway": "away",
        "date": "",
        "gameId": "544735279",
        "oppElo": null
      },
      {
        "opponent": "Colts",
        "homeAway": "away",
        "date": "",
        "gameId": "544735265",
        "oppElo": null
      },
      {
        "opponent": "Browns",
        "homeAway": "home",
        "date": "",
        "gameId": "544735250",
        "oppElo": null
      }
    ]
  },
  "Browns": {
    "team": "Browns",
    "conference": "AFC",
    "division": "AFC North",
    "games": 17,
    "schedule": [
      {
        "opponent": "Buccaneers",
        "homeAway": "home",
        "date": "",
        "gameId": "544735503",
        "oppElo": null
      },
      {
        "opponent": "Steelers",
        "homeAway": "away",
        "date": "",
        "gameId": "544735498",
        "oppElo": null
      },
      {
        "opponent": "Ravens",
        "homeAway": "home",
        "date": "",
        "gameId": "544735470",
        "oppElo": null
      },
      {
        "opponent": "Saints",
        "homeAway": "away",
        "date": "",
        "gameId": "544735457",
        "oppElo": null
      },
      {
        "opponent": "Titans",
        "homeAway": "home",
        "date": "",
        "gameId": "544735448",
        "oppElo": null
      },
      {
        "opponent": "Texans",
        "homeAway": "home",
        "date": "",
        "gameId": "544735425",
        "oppElo": null
      },
      {
        "opponent": "Chargers",
        "homeAway": "home",
        "date": "",
        "gameId": "544735403",
        "oppElo": null
      },
      {
        "opponent": "Bengals",
        "homeAway": "home",
        "date": "",
        "gameId": "544735394",
        "oppElo": null
      },
      {
        "opponent": "Jaguars",
        "homeAway": "away",
        "date": "",
        "gameId": "544735376",
        "oppElo": null
      },
      {
        "opponent": "Colts",
        "homeAway": "away",
        "date": "",
        "gameId": "544735361",
        "oppElo": null
      },
      {
        "opponent": "Commanders",
        "homeAway": "home",
        "date": "",
        "gameId": "544735343",
        "oppElo": null
      },
      {
        "opponent": "Bengals",
        "homeAway": "away",
        "date": "",
        "gameId": "544735329",
        "oppElo": null
      },
      {
        "opponent": "Steelers",
        "homeAway": "home",
        "date": "",
        "gameId": "544735322",
        "oppElo": null
      },
      {
        "opponent": "Bills",
        "homeAway": "away",
        "date": "",
        "gameId": "544735296",
        "oppElo": null
      },
      {
        "opponent": "Falcons",
        "homeAway": "home",
        "date": "",
        "gameId": "544735285",
        "oppElo": null
      },
      {
        "opponent": "Panthers",
        "homeAway": "away",
        "date": "",
        "gameId": "544735273",
        "oppElo": null
      },
      {
        "opponent": "Ravens",
        "homeAway": "away",
        "date": "",
        "gameId": "544735250",
        "oppElo": null
      }
    ]
  },
  "Buccaneers": {
    "team": "Buccaneers",
    "conference": "NFC",
    "division": "NFC South",
    "games": 17,
    "schedule": [
      {
        "opponent": "Browns",
        "homeAway": "away",
        "date": "",
        "gameId": "544735503",
        "oppElo": null
      },
      {
        "opponent": "Falcons",
        "homeAway": "home",
        "date": "",
        "gameId": "544735496",
        "oppElo": null
      },
      {
        "opponent": "Saints",
        "homeAway": "away",
        "date": "",
        "gameId": "544735479",
        "oppElo": null
      },
      {
        "opponent": "Panthers",
        "homeAway": "away",
        "date": "",
        "gameId": "544735458",
        "oppElo": null
      },
      {
        "opponent": "Broncos",
        "homeAway": "away",
        "date": "",
        "gameId": "544735442",
        "oppElo": null
      },
      {
        "opponent": "Panthers",
        "homeAway": "home",
        "date": "",
        "gameId": "544735435",
        "oppElo": null
      },
      {
        "opponent": "Packers",
        "homeAway": "home",
        "date": "",
        "gameId": "544735406",
        "oppElo": null
      },
      {
        "opponent": "Giants",
        "homeAway": "home",
        "date": "",
        "gameId": "544735389",
        "oppElo": null
      },
      {
        "opponent": "Saints",
        "homeAway": "home",
        "date": "",
        "gameId": "544735380",
        "oppElo": null
      },
      {
        "opponent": "Falcons",
        "homeAway": "away",
        "date": "",
        "gameId": "544735357",
        "oppElo": null
      },
      {
        "opponent": "Bengals",
        "homeAway": "home",
        "date": "",
        "gameId": "544735349",
        "oppElo": null
      },
      {
        "opponent": "Vikings",
        "homeAway": "away",
        "date": "",
        "gameId": "544735334",
        "oppElo": null
      },
      {
        "opponent": "Ravens",
        "homeAway": "away",
        "date": "",
        "gameId": "544735320",
        "oppElo": null
      },
      {
        "opponent": "Lions",
        "homeAway": "away",
        "date": "",
        "gameId": "544735306",
        "oppElo": null
      },
      {
        "opponent": "Steelers",
        "homeAway": "home",
        "date": "",
        "gameId": "544735282",
        "oppElo": null
      },
      {
        "opponent": "Bears",
        "homeAway": "home",
        "date": "",
        "gameId": "544735272",
        "oppElo": null
      },
      {
        "opponent": "Seahawks",
        "homeAway": "away",
        "date": "",
        "gameId": "544735253",
        "oppElo": null
      }
    ]
  },
  "Bengals": {
    "team": "Bengals",
    "conference": "AFC",
    "division": "AFC North",
    "games": 17,
    "schedule": [
      {
        "opponent": "Steelers",
        "homeAway": "home",
        "date": "",
        "gameId": "544735516",
        "oppElo": null
      },
      {
        "opponent": "Colts",
        "homeAway": "home",
        "date": "",
        "gameId": "544735493",
        "oppElo": null
      },
      {
        "opponent": "Jaguars",
        "homeAway": "home",
        "date": "",
        "gameId": "544735471",
        "oppElo": null
      },
      {
        "opponent": "Texans",
        "homeAway": "away",
        "date": "",
        "gameId": "544735466",
        "oppElo": null
      },
      {
        "opponent": "Raiders",
        "homeAway": "home",
        "date": "",
        "gameId": "544735449",
        "oppElo": null
      },
      {
        "opponent": "Dolphins",
        "homeAway": "away",
        "date": "",
        "gameId": "544735428",
        "oppElo": null
      },
      {
        "opponent": "Saints",
        "homeAway": "home",
        "date": "",
        "gameId": "544735419",
        "oppElo": null
      },
      {
        "opponent": "Ravens",
        "homeAway": "away",
        "date": "",
        "gameId": "544735397",
        "oppElo": null
      },
      {
        "opponent": "Browns",
        "homeAway": "away",
        "date": "",
        "gameId": "544735394",
        "oppElo": null
      },
      {
        "opponent": "Titans",
        "homeAway": "away",
        "date": "",
        "gameId": "544735367",
        "oppElo": null
      },
      {
        "opponent": "Cowboys",
        "homeAway": "home",
        "date": "",
        "gameId": "544735364",
        "oppElo": null
      },
      {
        "opponent": "Buccaneers",
        "homeAway": "away",
        "date": "",
        "gameId": "544735349",
        "oppElo": null
      },
      {
        "opponent": "Browns",
        "homeAway": "home",
        "date": "",
        "gameId": "544735329",
        "oppElo": null
      },
      {
        "opponent": "Panthers",
        "homeAway": "home",
        "date": "",
        "gameId": "544735302",
        "oppElo": null
      },
      {
        "opponent": "Ravens",
        "homeAway": "home",
        "date": "",
        "gameId": "544735279",
        "oppElo": null
      },
      {
        "opponent": "Falcons",
        "homeAway": "away",
        "date": "",
        "gameId": "544735264",
        "oppElo": null
      },
      {
        "opponent": "Steelers",
        "homeAway": "away",
        "date": "",
        "gameId": "544735246",
        "oppElo": null
      }
    ]
  },
  "Steelers": {
    "team": "Steelers",
    "conference": "AFC",
    "division": "AFC North",
    "games": 17,
    "schedule": [
      {
        "opponent": "Bengals",
        "homeAway": "away",
        "date": "",
        "gameId": "544735516",
        "oppElo": null
      },
      {
        "opponent": "Browns",
        "homeAway": "home",
        "date": "",
        "gameId": "544735498",
        "oppElo": null
      },
      {
        "opponent": "Eagles",
        "homeAway": "home",
        "date": "",
        "gameId": "544735480",
        "oppElo": null
      },
      {
        "opponent": "Ravens",
        "homeAway": "away",
        "date": "",
        "gameId": "544735463",
        "oppElo": null
      },
      {
        "opponent": "Texans",
        "homeAway": "away",
        "date": "",
        "gameId": "544735443",
        "oppElo": null
      },
      {
        "opponent": "Saints",
        "homeAway": "home",
        "date": "",
        "gameId": "544735426",
        "oppElo": null
      },
      {
        "opponent": "Jets",
        "homeAway": "away",
        "date": "",
        "gameId": "544735421",
        "oppElo": null
      },
      {
        "opponent": "Titans",
        "homeAway": "away",
        "date": "",
        "gameId": "544735401",
        "oppElo": null
      },
      {
        "opponent": "Panthers",
        "homeAway": "home",
        "date": "",
        "gameId": "544735391",
        "oppElo": null
      },
      {
        "opponent": "Jaguars",
        "homeAway": "home",
        "date": "",
        "gameId": "544735358",
        "oppElo": null
      },
      {
        "opponent": "Falcons",
        "homeAway": "away",
        "date": "",
        "gameId": "544735340",
        "oppElo": null
      },
      {
        "opponent": "Colts",
        "homeAway": "home",
        "date": "",
        "gameId": "544735325",
        "oppElo": null
      },
      {
        "opponent": "Browns",
        "homeAway": "away",
        "date": "",
        "gameId": "544735322",
        "oppElo": null
      },
      {
        "opponent": "Ravens",
        "homeAway": "home",
        "date": "",
        "gameId": "544735300",
        "oppElo": null
      },
      {
        "opponent": "Buccaneers",
        "homeAway": "away",
        "date": "",
        "gameId": "544735282",
        "oppElo": null
      },
      {
        "opponent": "Chiefs",
        "homeAway": "home",
        "date": "",
        "gameId": "544735261",
        "oppElo": null
      },
      {
        "opponent": "Bengals",
        "homeAway": "home",
        "date": "",
        "gameId": "544735246",
        "oppElo": null
      }
    ]
  },
  "Bills": {
    "team": "Bills",
    "conference": "AFC",
    "division": "AFC East",
    "games": 17,
    "schedule": [
      {
        "opponent": "Jets",
        "homeAway": "home",
        "date": "",
        "gameId": "544735515",
        "oppElo": null
      },
      {
        "opponent": "Lions",
        "homeAway": "home",
        "date": "",
        "gameId": "544735489",
        "oppElo": null
      },
      {
        "opponent": "Bears",
        "homeAway": "away",
        "date": "",
        "gameId": "544735474",
        "oppElo": null
      },
      {
        "opponent": "Broncos",
        "homeAway": "home",
        "date": "",
        "gameId": "544735460",
        "oppElo": null
      },
      {
        "opponent": "Dolphins",
        "homeAway": "away",
        "date": "",
        "gameId": "544735451",
        "oppElo": null
      },
      {
        "opponent": "Vikings",
        "homeAway": "home",
        "date": "",
        "gameId": "544735434",
        "oppElo": null
      },
      {
        "opponent": "Chiefs",
        "homeAway": "away",
        "date": "",
        "gameId": "544735396",
        "oppElo": null
      },
      {
        "opponent": "Rams",
        "homeAway": "home",
        "date": "",
        "gameId": "544735381",
        "oppElo": null
      },
      {
        "opponent": "Dolphins",
        "homeAway": "home",
        "date": "",
        "gameId": "544735379",
        "oppElo": null
      },
      {
        "opponent": "Raiders",
        "homeAway": "away",
        "date": "",
        "gameId": "544735362",
        "oppElo": null
      },
      {
        "opponent": "Patriots",
        "homeAway": "away",
        "date": "",
        "gameId": "544735338",
        "oppElo": null
      },
      {
        "opponent": "Packers",
        "homeAway": "away",
        "date": "",
        "gameId": "544735330",
        "oppElo": null
      },
      {
        "opponent": "Chargers",
        "homeAway": "home",
        "date": "",
        "gameId": "544735316",
        "oppElo": null
      },
      {
        "opponent": "Browns",
        "homeAway": "home",
        "date": "",
        "gameId": "544735296",
        "oppElo": null
      },
      {
        "opponent": "Texans",
        "homeAway": "away",
        "date": "",
        "gameId": "544735288",
        "oppElo": null
      },
      {
        "opponent": "Jets",
        "homeAway": "away",
        "date": "",
        "gameId": "544735271",
        "oppElo": null
      },
      {
        "opponent": "Patriots",
        "homeAway": "home",
        "date": "",
        "gameId": "544735249",
        "oppElo": null
      }
    ]
  },
  "Jets": {
    "team": "Jets",
    "conference": "AFC",
    "division": "AFC East",
    "games": 17,
    "schedule": [
      {
        "opponent": "Bills",
        "homeAway": "away",
        "date": "",
        "gameId": "544735515",
        "oppElo": null
      },
      {
        "opponent": "Patriots",
        "homeAway": "home",
        "date": "",
        "gameId": "544735487",
        "oppElo": null
      },
      {
        "opponent": "Raiders",
        "homeAway": "home",
        "date": "",
        "gameId": "544735482",
        "oppElo": null
      },
      {
        "opponent": "Bears",
        "homeAway": "home",
        "date": "",
        "gameId": "544735459",
        "oppElo": null
      },
      {
        "opponent": "Lions",
        "homeAway": "away",
        "date": "",
        "gameId": "544735444",
        "oppElo": null
      },
      {
        "opponent": "Chargers",
        "homeAway": "away",
        "date": "",
        "gameId": "544735433",
        "oppElo": null
      },
      {
        "opponent": "Steelers",
        "homeAway": "home",
        "date": "",
        "gameId": "544735421",
        "oppElo": null
      },
      {
        "opponent": "Vikings",
        "homeAway": "away",
        "date": "",
        "gameId": "544735405",
        "oppElo": null
      },
      {
        "opponent": "Chiefs",
        "homeAway": "home",
        "date": "",
        "gameId": "544735384",
        "oppElo": null
      },
      {
        "opponent": "Patriots",
        "homeAway": "away",
        "date": "",
        "gameId": "544735375",
        "oppElo": null
      },
      {
        "opponent": "Packers",
        "homeAway": "home",
        "date": "",
        "gameId": "544735351",
        "oppElo": null
      },
      {
        "opponent": "Cardinals",
        "homeAway": "home",
        "date": "",
        "gameId": "544735323",
        "oppElo": null
      },
      {
        "opponent": "Broncos",
        "homeAway": "away",
        "date": "",
        "gameId": "544735315",
        "oppElo": null
      },
      {
        "opponent": "Dolphins",
        "homeAway": "home",
        "date": "",
        "gameId": "544735303",
        "oppElo": null
      },
      {
        "opponent": "Colts",
        "homeAway": "away",
        "date": "",
        "gameId": "544735283",
        "oppElo": null
      },
      {
        "opponent": "Bills",
        "homeAway": "home",
        "date": "",
        "gameId": "544735271",
        "oppElo": null
      },
      {
        "opponent": "Dolphins",
        "homeAway": "away",
        "date": "",
        "gameId": "544735247",
        "oppElo": null
      }
    ]
  },
  "Colts": {
    "team": "Colts",
    "conference": "AFC",
    "division": "AFC South",
    "games": 17,
    "schedule": [
      {
        "opponent": "Titans",
        "homeAway": "home",
        "date": "",
        "gameId": "544735513",
        "oppElo": null
      },
      {
        "opponent": "Bengals",
        "homeAway": "away",
        "date": "",
        "gameId": "544735493",
        "oppElo": null
      },
      {
        "opponent": "Titans",
        "homeAway": "away",
        "date": "",
        "gameId": "544735476",
        "oppElo": null
      },
      {
        "opponent": "Cowboys",
        "homeAway": "home",
        "date": "",
        "gameId": "544735465",
        "oppElo": null
      },
      {
        "opponent": "Giants",
        "homeAway": "away",
        "date": "",
        "gameId": "544735452",
        "oppElo": null
      },
      {
        "opponent": "Jaguars",
        "homeAway": "away",
        "date": "",
        "gameId": "544735436",
        "oppElo": null
      },
      {
        "opponent": "Eagles",
        "homeAway": "home",
        "date": "",
        "gameId": "544735417",
        "oppElo": null
      },
      {
        "opponent": "Texans",
        "homeAway": "home",
        "date": "",
        "gameId": "544735400",
        "oppElo": null
      },
      {
        "opponent": "Commanders",
        "homeAway": "away",
        "date": "",
        "gameId": "544735392",
        "oppElo": null
      },
      {
        "opponent": "Chiefs",
        "homeAway": "away",
        "date": "",
        "gameId": "544735378",
        "oppElo": null
      },
      {
        "opponent": "Browns",
        "homeAway": "home",
        "date": "",
        "gameId": "544735361",
        "oppElo": null
      },
      {
        "opponent": "Steelers",
        "homeAway": "away",
        "date": "",
        "gameId": "544735325",
        "oppElo": null
      },
      {
        "opponent": "Jaguars",
        "homeAway": "home",
        "date": "",
        "gameId": "544735321",
        "oppElo": null
      },
      {
        "opponent": "Texans",
        "homeAway": "away",
        "date": "",
        "gameId": "544735305",
        "oppElo": null
      },
      {
        "opponent": "Jets",
        "homeAway": "home",
        "date": "",
        "gameId": "544735283",
        "oppElo": null
      },
      {
        "opponent": "Ravens",
        "homeAway": "home",
        "date": "",
        "gameId": "544735265",
        "oppElo": null
      },
      {
        "opponent": "Packers",
        "homeAway": "home",
        "date": "",
        "gameId": "544735260",
        "oppElo": null
      }
    ]
  },
  "Titans": {
    "team": "Titans",
    "conference": "AFC",
    "division": "AFC South",
    "games": 17,
    "schedule": [
      {
        "opponent": "Colts",
        "homeAway": "away",
        "date": "",
        "gameId": "544735513",
        "oppElo": null
      },
      {
        "opponent": "Commanders",
        "homeAway": "home",
        "date": "",
        "gameId": "544735492",
        "oppElo": null
      },
      {
        "opponent": "Colts",
        "homeAway": "home",
        "date": "",
        "gameId": "544735476",
        "oppElo": null
      },
      {
        "opponent": "Giants",
        "homeAway": "home",
        "date": "",
        "gameId": "544735455",
        "oppElo": null
      },
      {
        "opponent": "Browns",
        "homeAway": "away",
        "date": "",
        "gameId": "544735448",
        "oppElo": null
      },
      {
        "opponent": "Ravens",
        "homeAway": "away",
        "date": "",
        "gameId": "544735420",
        "oppElo": null
      },
      {
        "opponent": "Steelers",
        "homeAway": "home",
        "date": "",
        "gameId": "544735401",
        "oppElo": null
      },
      {
        "opponent": "Broncos",
        "homeAway": "away",
        "date": "",
        "gameId": "544735385",
        "oppElo": null
      },
      {
        "opponent": "Bengals",
        "homeAway": "home",
        "date": "",
        "gameId": "544735367",
        "oppElo": null
      },
      {
        "opponent": "Texans",
        "homeAway": "home",
        "date": "",
        "gameId": "544735365",
        "oppElo": null
      },
      {
        "opponent": "Cowboys",
        "homeAway": "away",
        "date": "",
        "gameId": "544735350",
        "oppElo": null
      },
      {
        "opponent": "Jaguars",
        "homeAway": "away",
        "date": "",
        "gameId": "544735332",
        "oppElo": null
      },
      {
        "opponent": "Texans",
        "homeAway": "away",
        "date": "",
        "gameId": "544735312",
        "oppElo": null
      },
      {
        "opponent": "Jaguars",
        "homeAway": "home",
        "date": "",
        "gameId": "544735298",
        "oppElo": null
      },
      {
        "opponent": "Lions",
        "homeAway": "home",
        "date": "",
        "gameId": "544735291",
        "oppElo": null
      },
      {
        "opponent": "Patriots",
        "homeAway": "home",
        "date": "",
        "gameId": "544735266",
        "oppElo": null
      },
      {
        "opponent": "Eagles",
        "homeAway": "away",
        "date": "",
        "gameId": "544735252",
        "oppElo": null
      }
    ]
  },
  "Packers": {
    "team": "Packers",
    "conference": "NFC",
    "division": "NFC North",
    "games": 17,
    "schedule": [
      {
        "opponent": "Vikings",
        "homeAway": "home",
        "date": "",
        "gameId": "544735511",
        "oppElo": null
      },
      {
        "opponent": "Dolphins",
        "homeAway": "away",
        "date": "",
        "gameId": "544735490",
        "oppElo": null
      },
      {
        "opponent": "Lions",
        "homeAway": "away",
        "date": "",
        "gameId": "544735478",
        "oppElo": null
      },
      {
        "opponent": "Falcons",
        "homeAway": "away",
        "date": "",
        "gameId": "544735461",
        "oppElo": null
      },
      {
        "opponent": "Vikings",
        "homeAway": "away",
        "date": "",
        "gameId": "544735440",
        "oppElo": null
      },
      {
        "opponent": "Patriots",
        "homeAway": "home",
        "date": "",
        "gameId": "544735427",
        "oppElo": null
      },
      {
        "opponent": "Bears",
        "homeAway": "away",
        "date": "",
        "gameId": "544735410",
        "oppElo": null
      },
      {
        "opponent": "Buccaneers",
        "homeAway": "away",
        "date": "",
        "gameId": "544735406",
        "oppElo": null
      },
      {
        "opponent": "Eagles",
        "homeAway": "away",
        "date": "",
        "gameId": "544735382",
        "oppElo": null
      },
      {
        "opponent": "Bears",
        "homeAway": "home",
        "date": "",
        "gameId": "544735360",
        "oppElo": null
      },
      {
        "opponent": "Jets",
        "homeAway": "away",
        "date": "",
        "gameId": "544735351",
        "oppElo": null
      },
      {
        "opponent": "Bills",
        "homeAway": "home",
        "date": "",
        "gameId": "544735330",
        "oppElo": null
      },
      {
        "opponent": "Panthers",
        "homeAway": "home",
        "date": "",
        "gameId": "544735318",
        "oppElo": null
      },
      {
        "opponent": "Cardinals",
        "homeAway": "home",
        "date": "",
        "gameId": "544735295",
        "oppElo": null
      },
      {
        "opponent": "Saints",
        "homeAway": "home",
        "date": "",
        "gameId": "544735284",
        "oppElo": null
      },
      {
        "opponent": "Lions",
        "homeAway": "home",
        "date": "",
        "gameId": "544735263",
        "oppElo": null
      },
      {
        "opponent": "Colts",
        "homeAway": "away",
        "date": "",
        "gameId": "544735260",
        "oppElo": null
      }
    ]
  },
  "Vikings": {
    "team": "Vikings",
    "conference": "NFC",
    "division": "NFC North",
    "games": 17,
    "schedule": [
      {
        "opponent": "Packers",
        "homeAway": "away",
        "date": "",
        "gameId": "544735511",
        "oppElo": null
      },
      {
        "opponent": "Panthers",
        "homeAway": "away",
        "date": "",
        "gameId": "544735499",
        "oppElo": null
      },
      {
        "opponent": "Commanders",
        "homeAway": "away",
        "date": "",
        "gameId": "544735472",
        "oppElo": null
      },
      {
        "opponent": "Dolphins",
        "homeAway": "home",
        "date": "",
        "gameId": "544735462",
        "oppElo": null
      },
      {
        "opponent": "Packers",
        "homeAway": "home",
        "date": "",
        "gameId": "544735440",
        "oppElo": null
      },
      {
        "opponent": "Bills",
        "homeAway": "away",
        "date": "",
        "gameId": "544735434",
        "oppElo": null
      },
      {
        "opponent": "Jets",
        "homeAway": "home",
        "date": "",
        "gameId": "544735405",
        "oppElo": null
      },
      {
        "opponent": "Patriots",
        "homeAway": "away",
        "date": "",
        "gameId": "544735390",
        "oppElo": null
      },
      {
        "opponent": "Texans",
        "homeAway": "away",
        "date": "",
        "gameId": "544735369",
        "oppElo": null
      },
      {
        "opponent": "Lions",
        "homeAway": "away",
        "date": "",
        "gameId": "544735363",
        "oppElo": null
      },
      {
        "opponent": "Bears",
        "homeAway": "home",
        "date": "",
        "gameId": "544735342",
        "oppElo": null
      },
      {
        "opponent": "Buccaneers",
        "homeAway": "home",
        "date": "",
        "gameId": "544735334",
        "oppElo": null
      },
      {
        "opponent": "Falcons",
        "homeAway": "home",
        "date": "",
        "gameId": "544735319",
        "oppElo": null
      },
      {
        "opponent": "Rams",
        "homeAway": "home",
        "date": "",
        "gameId": "544735297",
        "oppElo": null
      },
      {
        "opponent": "Bears",
        "homeAway": "away",
        "date": "",
        "gameId": "544735278",
        "oppElo": null
      },
      {
        "opponent": "Saints",
        "homeAway": "away",
        "date": "",
        "gameId": "544735267",
        "oppElo": null
      },
      {
        "opponent": "Lions",
        "homeAway": "home",
        "date": "",
        "gameId": "544735256",
        "oppElo": null
      }
    ]
  },
  "Patriots": {
    "team": "Patriots",
    "conference": "AFC",
    "division": "AFC East",
    "games": 17,
    "schedule": [
      {
        "opponent": "Dolphins",
        "homeAway": "home",
        "date": "",
        "gameId": "544735510",
        "oppElo": null
      },
      {
        "opponent": "Jets",
        "homeAway": "away",
        "date": "",
        "gameId": "544735487",
        "oppElo": null
      },
      {
        "opponent": "Chargers",
        "homeAway": "home",
        "date": "",
        "gameId": "544735483",
        "oppElo": null
      },
      {
        "opponent": "Lions",
        "homeAway": "home",
        "date": "",
        "gameId": "544735464",
        "oppElo": null
      },
      {
        "opponent": "Seahawks",
        "homeAway": "home",
        "date": "",
        "gameId": "544735450",
        "oppElo": null
      },
      {
        "opponent": "Packers",
        "homeAway": "away",
        "date": "",
        "gameId": "544735427",
        "oppElo": null
      },
      {
        "opponent": "Raiders",
        "homeAway": "away",
        "date": "",
        "gameId": "544735416",
        "oppElo": null
      },
      {
        "opponent": "Vikings",
        "homeAway": "home",
        "date": "",
        "gameId": "544735390",
        "oppElo": null
      },
      {
        "opponent": "Jets",
        "homeAway": "home",
        "date": "",
        "gameId": "544735375",
        "oppElo": null
      },
      {
        "opponent": "Ravens",
        "homeAway": "home",
        "date": "",
        "gameId": "544735359",
        "oppElo": null
      },
      {
        "opponent": "Bills",
        "homeAway": "home",
        "date": "",
        "gameId": "544735338",
        "oppElo": null
      },
      {
        "opponent": "Dolphins",
        "homeAway": "away",
        "date": "",
        "gameId": "544735331",
        "oppElo": null
      },
      {
        "opponent": "Chiefs",
        "homeAway": "away",
        "date": "",
        "gameId": "544735309",
        "oppElo": null
      },
      {
        "opponent": "Bears",
        "homeAway": "away",
        "date": "",
        "gameId": "544735294",
        "oppElo": null
      },
      {
        "opponent": "Broncos",
        "homeAway": "home",
        "date": "",
        "gameId": "544735281",
        "oppElo": null
      },
      {
        "opponent": "Titans",
        "homeAway": "away",
        "date": "",
        "gameId": "544735266",
        "oppElo": null
      },
      {
        "opponent": "Bills",
        "homeAway": "away",
        "date": "",
        "gameId": "544735249",
        "oppElo": null
      }
    ]
  },
  "Dolphins": {
    "team": "Dolphins",
    "conference": "AFC",
    "division": "AFC East",
    "games": 17,
    "schedule": [
      {
        "opponent": "Patriots",
        "homeAway": "away",
        "date": "",
        "gameId": "544735510",
        "oppElo": null
      },
      {
        "opponent": "Packers",
        "homeAway": "home",
        "date": "",
        "gameId": "544735490",
        "oppElo": null
      },
      {
        "opponent": "Broncos",
        "homeAway": "away",
        "date": "",
        "gameId": "544735481",
        "oppElo": null
      },
      {
        "opponent": "Vikings",
        "homeAway": "away",
        "date": "",
        "gameId": "544735462",
        "oppElo": null
      },
      {
        "opponent": "Bills",
        "homeAway": "home",
        "date": "",
        "gameId": "544735451",
        "oppElo": null
      },
      {
        "opponent": "Bengals",
        "homeAway": "home",
        "date": "",
        "gameId": "544735428",
        "oppElo": null
      },
      {
        "opponent": "Jaguars",
        "homeAway": "away",
        "date": "",
        "gameId": "544735398",
        "oppElo": null
      },
      {
        "opponent": "Chargers",
        "homeAway": "away",
        "date": "",
        "gameId": "544735383",
        "oppElo": null
      },
      {
        "opponent": "Bills",
        "homeAway": "away",
        "date": "",
        "gameId": "544735379",
        "oppElo": null
      },
      {
        "opponent": "49ers",
        "homeAway": "home",
        "date": "",
        "gameId": "544735356",
        "oppElo": null
      },
      {
        "opponent": "Lions",
        "homeAway": "away",
        "date": "",
        "gameId": "544735347",
        "oppElo": null
      },
      {
        "opponent": "Patriots",
        "homeAway": "home",
        "date": "",
        "gameId": "544735331",
        "oppElo": null
      },
      {
        "opponent": "Bears",
        "homeAway": "home",
        "date": "",
        "gameId": "544735311",
        "oppElo": null
      },
      {
        "opponent": "Jets",
        "homeAway": "away",
        "date": "",
        "gameId": "544735303",
        "oppElo": null
      },
      {
        "opponent": "Chiefs",
        "homeAway": "home",
        "date": "",
        "gameId": "544735277",
        "oppElo": null
      },
      {
        "opponent": "Raiders",
        "homeAway": "home",
        "date": "",
        "gameId": "544735269",
        "oppElo": null
      },
      {
        "opponent": "Jets",
        "homeAway": "home",
        "date": "",
        "gameId": "544735247",
        "oppElo": null
      }
    ]
  },
  "Texans": {
    "team": "Texans",
    "conference": "AFC",
    "division": "AFC South",
    "games": 17,
    "schedule": [
      {
        "opponent": "Jaguars",
        "homeAway": "home",
        "date": "",
        "gameId": "544735509",
        "oppElo": null
      },
      {
        "opponent": "Ravens",
        "homeAway": "away",
        "date": "",
        "gameId": "544735494",
        "oppElo": null
      },
      {
        "opponent": "Giants",
        "homeAway": "home",
        "date": "",
        "gameId": "544735477",
        "oppElo": null
      },
      {
        "opponent": "Bengals",
        "homeAway": "home",
        "date": "",
        "gameId": "544735466",
        "oppElo": null
      },
      {
        "opponent": "Steelers",
        "homeAway": "home",
        "date": "",
        "gameId": "544735443",
        "oppElo": null
      },
      {
        "opponent": "Browns",
        "homeAway": "away",
        "date": "",
        "gameId": "544735425",
        "oppElo": null
      },
      {
        "opponent": "Jaguars",
        "homeAway": "away",
        "date": "",
        "gameId": "544735412",
        "oppElo": null
      },
      {
        "opponent": "Colts",
        "homeAway": "away",
        "date": "",
        "gameId": "544735400",
        "oppElo": null
      },
      {
        "opponent": "Vikings",
        "homeAway": "home",
        "date": "",
        "gameId": "544735369",
        "oppElo": null
      },
      {
        "opponent": "Titans",
        "homeAway": "away",
        "date": "",
        "gameId": "544735365",
        "oppElo": null
      },
      {
        "opponent": "Eagles",
        "homeAway": "away",
        "date": "",
        "gameId": "544735344",
        "oppElo": null
      },
      {
        "opponent": "Cowboys",
        "homeAway": "away",
        "date": "",
        "gameId": "544735324",
        "oppElo": null
      },
      {
        "opponent": "Titans",
        "homeAway": "home",
        "date": "",
        "gameId": "544735312",
        "oppElo": null
      },
      {
        "opponent": "Colts",
        "homeAway": "home",
        "date": "",
        "gameId": "544735305",
        "oppElo": null
      },
      {
        "opponent": "Bills",
        "homeAway": "home",
        "date": "",
        "gameId": "544735288",
        "oppElo": null
      },
      {
        "opponent": "Chargers",
        "homeAway": "away",
        "date": "",
        "gameId": "544735268",
        "oppElo": null
      },
      {
        "opponent": "Commanders",
        "homeAway": "home",
        "date": "",
        "gameId": "544735254",
        "oppElo": null
      }
    ]
  },
  "Jaguars": {
    "team": "Jaguars",
    "conference": "AFC",
    "division": "AFC South",
    "games": 17,
    "schedule": [
      {
        "opponent": "Texans",
        "homeAway": "away",
        "date": "",
        "gameId": "544735509",
        "oppElo": null
      },
      {
        "opponent": "Cowboys",
        "homeAway": "home",
        "date": "",
        "gameId": "544735491",
        "oppElo": null
      },
      {
        "opponent": "Bengals",
        "homeAway": "away",
        "date": "",
        "gameId": "544735471",
        "oppElo": null
      },
      {
        "opponent": "Eagles",
        "homeAway": "home",
        "date": "",
        "gameId": "544735467",
        "oppElo": null
      },
      {
        "opponent": "Ravens",
        "homeAway": "home",
        "date": "",
        "gameId": "544735446",
        "oppElo": null
      },
      {
        "opponent": "Colts",
        "homeAway": "home",
        "date": "",
        "gameId": "544735436",
        "oppElo": null
      },
      {
        "opponent": "Texans",
        "homeAway": "home",
        "date": "",
        "gameId": "544735412",
        "oppElo": null
      },
      {
        "opponent": "Dolphins",
        "homeAway": "home",
        "date": "",
        "gameId": "544735398",
        "oppElo": null
      },
      {
        "opponent": "Browns",
        "homeAway": "home",
        "date": "",
        "gameId": "544735376",
        "oppElo": null
      },
      {
        "opponent": "Steelers",
        "homeAway": "away",
        "date": "",
        "gameId": "544735358",
        "oppElo": null
      },
      {
        "opponent": "Raiders",
        "homeAway": "away",
        "date": "",
        "gameId": "544735348",
        "oppElo": null
      },
      {
        "opponent": "Titans",
        "homeAway": "home",
        "date": "",
        "gameId": "544735332",
        "oppElo": null
      },
      {
        "opponent": "Colts",
        "homeAway": "away",
        "date": "",
        "gameId": "544735321",
        "oppElo": null
      },
      {
        "opponent": "Titans",
        "homeAway": "away",
        "date": "",
        "gameId": "544735298",
        "oppElo": null
      },
      {
        "opponent": "Giants",
        "homeAway": "away",
        "date": "",
        "gameId": "544735289",
        "oppElo": null
      },
      {
        "opponent": "Commanders",
        "homeAway": "away",
        "date": "",
        "gameId": "544735274",
        "oppElo": null
      },
      {
        "opponent": "Bears",
        "homeAway": "home",
        "date": "",
        "gameId": "544735258",
        "oppElo": null
      }
    ]
  },
  "Giants": {
    "team": "Giants",
    "conference": "NFC",
    "division": "NFC East",
    "games": 17,
    "schedule": [
      {
        "opponent": "Rams",
        "homeAway": "home",
        "date": "",
        "gameId": "544735506",
        "oppElo": null
      },
      {
        "opponent": "Cardinals",
        "homeAway": "away",
        "date": "",
        "gameId": "544735495",
        "oppElo": null
      },
      {
        "opponent": "Texans",
        "homeAway": "away",
        "date": "",
        "gameId": "544735477",
        "oppElo": null
      },
      {
        "opponent": "Titans",
        "homeAway": "away",
        "date": "",
        "gameId": "544735455",
        "oppElo": null
      },
      {
        "opponent": "Colts",
        "homeAway": "home",
        "date": "",
        "gameId": "544735452",
        "oppElo": null
      },
      {
        "opponent": "Commanders",
        "homeAway": "home",
        "date": "",
        "gameId": "544735430",
        "oppElo": null
      },
      {
        "opponent": "Cowboys",
        "homeAway": "away",
        "date": "",
        "gameId": "544735422",
        "oppElo": null
      },
      {
        "opponent": "Seahawks",
        "homeAway": "home",
        "date": "",
        "gameId": "544735399",
        "oppElo": null
      },
      {
        "opponent": "Buccaneers",
        "homeAway": "away",
        "date": "",
        "gameId": "544735389",
        "oppElo": null
      },
      {
        "opponent": "Ravens",
        "homeAway": "away",
        "date": "",
        "gameId": "544735368",
        "oppElo": null
      },
      {
        "opponent": "Eagles",
        "homeAway": "home",
        "date": "",
        "gameId": "544735353",
        "oppElo": null
      },
      {
        "opponent": "49ers",
        "homeAway": "away",
        "date": "",
        "gameId": "544735333",
        "oppElo": null
      },
      {
        "opponent": "Lions",
        "homeAway": "home",
        "date": "",
        "gameId": "544735313",
        "oppElo": null
      },
      {
        "opponent": "Commanders",
        "homeAway": "away",
        "date": "",
        "gameId": "544735301",
        "oppElo": null
      },
      {
        "opponent": "Jaguars",
        "homeAway": "home",
        "date": "",
        "gameId": "544735289",
        "oppElo": null
      },
      {
        "opponent": "Eagles",
        "homeAway": "away",
        "date": "",
        "gameId": "544735276",
        "oppElo": null
      },
      {
        "opponent": "Cowboys",
        "homeAway": "home",
        "date": "",
        "gameId": "544735259",
        "oppElo": null
      }
    ]
  },
  "Rams": {
    "team": "Rams",
    "conference": "NFC",
    "division": "NFC West",
    "games": 17,
    "schedule": [
      {
        "opponent": "Giants",
        "homeAway": "away",
        "date": "",
        "gameId": "544735506",
        "oppElo": null
      },
      {
        "opponent": "Chargers",
        "homeAway": "away",
        "date": "",
        "gameId": "544735485",
        "oppElo": null
      },
      {
        "opponent": "Cowboys",
        "homeAway": "home",
        "date": "",
        "gameId": "544735484",
        "oppElo": null
      },
      {
        "opponent": "Commanders",
        "homeAway": "away",
        "date": "",
        "gameId": "544735456",
        "oppElo": null
      },
      {
        "opponent": "Cardinals",
        "homeAway": "home",
        "date": "",
        "gameId": "544735445",
        "oppElo": null
      },
      {
        "opponent": "49ers",
        "homeAway": "away",
        "date": "",
        "gameId": "544735411",
        "oppElo": null
      },
      {
        "opponent": "Eagles",
        "homeAway": "home",
        "date": "",
        "gameId": "544735404",
        "oppElo": null
      },
      {
        "opponent": "Bills",
        "homeAway": "away",
        "date": "",
        "gameId": "544735381",
        "oppElo": null
      },
      {
        "opponent": "Cardinals",
        "homeAway": "away",
        "date": "",
        "gameId": "544735373",
        "oppElo": null
      },
      {
        "opponent": "Seahawks",
        "homeAway": "home",
        "date": "",
        "gameId": "544735352",
        "oppElo": null
      },
      {
        "opponent": "Chiefs",
        "homeAway": "home",
        "date": "",
        "gameId": "544735337",
        "oppElo": null
      },
      {
        "opponent": "Seahawks",
        "homeAway": "away",
        "date": "",
        "gameId": "544735335",
        "oppElo": null
      },
      {
        "opponent": "Raiders",
        "homeAway": "home",
        "date": "",
        "gameId": "544735317",
        "oppElo": null
      },
      {
        "opponent": "Vikings",
        "homeAway": "away",
        "date": "",
        "gameId": "544735297",
        "oppElo": null
      },
      {
        "opponent": "49ers",
        "homeAway": "home",
        "date": "",
        "gameId": "544735292",
        "oppElo": null
      },
      {
        "opponent": "Broncos",
        "homeAway": "away",
        "date": "",
        "gameId": "544735275",
        "oppElo": null
      },
      {
        "opponent": "Falcons",
        "homeAway": "home",
        "date": "",
        "gameId": "544735257",
        "oppElo": null
      }
    ]
  },
  "Panthers": {
    "team": "Panthers",
    "conference": "NFC",
    "division": "NFC South",
    "games": 16,
    "schedule": [
      {
        "opponent": "Vikings",
        "homeAway": "home",
        "date": "",
        "gameId": "544735499",
        "oppElo": null
      },
      {
        "opponent": "Falcons",
        "homeAway": "away",
        "date": "",
        "gameId": "544735473",
        "oppElo": null
      },
      {
        "opponent": "Buccaneers",
        "homeAway": "home",
        "date": "",
        "gameId": "544735458",
        "oppElo": null
      },
      {
        "opponent": "Saints",
        "homeAway": "away",
        "date": "",
        "gameId": "544735437",
        "oppElo": null
      },
      {
        "opponent": "Buccaneers",
        "homeAway": "away",
        "date": "",
        "gameId": "544735435",
        "oppElo": null
      },
      {
        "opponent": "Falcons",
        "homeAway": "home",
        "date": "",
        "gameId": "544735414",
        "oppElo": null
      },
      {
        "opponent": "Cardinals",
        "homeAway": "away",
        "date": "",
        "gameId": "544735402",
        "oppElo": null
      },
      {
        "opponent": "Steelers",
        "homeAway": "away",
        "date": "",
        "gameId": "544735391",
        "oppElo": null
      },
      {
        "opponent": "Saints",
        "homeAway": "home",
        "date": "",
        "gameId": "544735366",
        "oppElo": null
      },
      {
        "opponent": "Ravens",
        "homeAway": "home",
        "date": "",
        "gameId": "544735341",
        "oppElo": null
      },
      {
        "opponent": "Lions",
        "homeAway": "home",
        "date": "",
        "gameId": "544735336",
        "oppElo": null
      },
      {
        "opponent": "Packers",
        "homeAway": "away",
        "date": "",
        "gameId": "544735318",
        "oppElo": null
      },
      {
        "opponent": "Bengals",
        "homeAway": "away",
        "date": "",
        "gameId": "544735302",
        "oppElo": null
      },
      {
        "opponent": "Eagles",
        "homeAway": "home",
        "date": "",
        "gameId": "544735280",
        "oppElo": null
      },
      {
        "opponent": "Browns",
        "homeAway": "home",
        "date": "",
        "gameId": "544735273",
        "oppElo": null
      },
      {
        "opponent": "Chiefs",
        "homeAway": "away",
        "date": "",
        "gameId": "544735245",
        "oppElo": null
      }
    ]
  },
  "Bears": {
    "team": "Bears",
    "conference": "NFC",
    "division": "NFC North",
    "games": 16,
    "schedule": [
      {
        "opponent": "Saints",
        "homeAway": "home",
        "date": "",
        "gameId": "544735486",
        "oppElo": null
      },
      {
        "opponent": "Bills",
        "homeAway": "home",
        "date": "",
        "gameId": "544735474",
        "oppElo": null
      },
      {
        "opponent": "Jets",
        "homeAway": "away",
        "date": "",
        "gameId": "544735459",
        "oppElo": null
      },
      {
        "opponent": "Falcons",
        "homeAway": "away",
        "date": "",
        "gameId": "544735447",
        "oppElo": null
      },
      {
        "opponent": "Lions",
        "homeAway": "home",
        "date": "",
        "gameId": "544735432",
        "oppElo": null
      },
      {
        "opponent": "Packers",
        "homeAway": "home",
        "date": "",
        "gameId": "544735410",
        "oppElo": null
      },
      {
        "opponent": "Lions",
        "homeAway": "away",
        "date": "",
        "gameId": "544735408",
        "oppElo": null
      },
      {
        "opponent": "Cowboys",
        "homeAway": "away",
        "date": "",
        "gameId": "544735388",
        "oppElo": null
      },
      {
        "opponent": "49ers",
        "homeAway": "home",
        "date": "",
        "gameId": "544735371",
        "oppElo": null
      },
      {
        "opponent": "Packers",
        "homeAway": "away",
        "date": "",
        "gameId": "544735360",
        "oppElo": null
      },
      {
        "opponent": "Vikings",
        "homeAway": "away",
        "date": "",
        "gameId": "544735342",
        "oppElo": null
      },
      {
        "opponent": "Dolphins",
        "homeAway": "away",
        "date": "",
        "gameId": "544735311",
        "oppElo": null
      },
      {
        "opponent": "Patriots",
        "homeAway": "home",
        "date": "",
        "gameId": "544735294",
        "oppElo": null
      },
      {
        "opponent": "Vikings",
        "homeAway": "home",
        "date": "",
        "gameId": "544735278",
        "oppElo": null
      },
      {
        "opponent": "Buccaneers",
        "homeAway": "away",
        "date": "",
        "gameId": "544735272",
        "oppElo": null
      },
      {
        "opponent": "Jaguars",
        "homeAway": "away",
        "date": "",
        "gameId": "544735258",
        "oppElo": null
      }
    ]
  }
}